{
  "schema_version": 1,
  "artifact_type": "raw_data",
  "metadata": {
    "artifact_type": "raw_data",
    "file_name": "04_njf_self_bias.cir",
    "file_path": "E:\\Individual Project\\circuit_design_ai\\TestWork\\op_analysis\\04_njf_self_bias.cir",
    "analysis_type": "op",
    "timestamp": "2026-04-22T10:26:54.349901",
    "success": true,
    "executor": "spice",
    "duration_seconds": 0.007215738296508789,
    "analysis_command": ".op",
    "x_axis_kind": "none",
    "x_axis_label": "X",
    "x_axis_scale": "none",
    "requested_x_range": null,
    "actual_x_range": null
  },
  "summary": {
    "row_count": 1,
    "signal_count": 5,
    "x_axis_label": "Index"
  },
  "files": {
    "csv": "raw_data.csv"
  },
  "data": {
    "columns": [
      "Index",
      "V(drain)",
      "V(gate)",
      "V(src)",
      "V(vdd)",
      "I(VDD)"
    ],
    "rows": [
      {
        "Index": 0.0,
        "V(drain)": 7.427400770889315,
        "V(gate)": 9.634886995079592e-06,
        "V(src)": 2.1403655754074067,
        "V(vdd)": 12.0,
        "I(VDD)": -0.0009728934530022733
      }
    ],
    "series": [
      {
        "name": "V(drain)",
        "x": [
          0.0
        ],
        "y": [
          7.427400770889315
        ],
        "point_count": 1
      },
      {
        "name": "V(gate)",
        "x": [
          0.0
        ],
        "y": [
          9.634886995079592e-06
        ],
        "point_count": 1
      },
      {
        "name": "V(src)",
        "x": [
          0.0
        ],
        "y": [
          2.1403655754074067
        ],
        "point_count": 1
      },
      {
        "name": "V(vdd)",
        "x": [
          0.0
        ],
        "y": [
          12.0
        ],
        "point_count": 1
      },
      {
        "name": "I(VDD)",
        "x": [
          0.0
        ],
        "y": [
          -0.0009728934530022733
        ],
        "point_count": 1
      }
    ]
  }
}